LICENSE
MANIFEST.in
README.md
setup.py
pytest_notice/__init__.py
pytest_notice/plugin.py
pytest_notice.egg-info/PKG-INFO
pytest_notice.egg-info/SOURCES.txt
pytest_notice.egg-info/dependency_links.txt
pytest_notice.egg-info/entry_points.txt
pytest_notice.egg-info/requires.txt
pytest_notice.egg-info/top_level.txt
pytest_notice.egg-info/zip-safe