Metadata-Version: 1.1
Name: pytest-notice
Version: 0.1
Summary: Send pytest execution result email
Home-page: https://github.com/hanzhichao/pytest-notice
Author: Han Zhichao
Author-email: superhin@126.com
License: MIT license
Keywords: pytest,py.test,pytest-notice
Platform: UNKNOWN
Classifier: Framework :: Pytest
Classifier: Programming Language :: Python
Classifier: Topic :: Software Development :: Testing
Classifier: Programming Language :: Python :: 2.7
Classifier: Programming Language :: Python :: 3.7
